{
  "db_name": "PostgreSQL",
  "query": "SELECT \n            market_order.id,\n            location.id as location_id,\n            market_order.item_unique_name,\n            quality_level, \n            enchantment_level, \n            unit_price_silver, \n            amount, \n            auction_type, \n            expires_at, \n            updated_at,\n            created_at  \n        FROM \n            market_order, \n            location, \n            localized_name\n        WHERE \n            location_id = location.id\n            AND localized_name.item_unique_name = market_order.item_unique_name\n            AND expires_at > NOW()\n            AND ( $3::TEXT IS NULL OR location.id = $3 )\n            AND ( $4::TEXT IS NULL OR auction_type = $4 )\n            AND ( $5::INT IS NULL OR quality_level = $5 )\n            AND ( $6::INT IS NULL OR enchantment_level = $6 )\n            AND ( $7::DATE IS NULL OR DATE(updated_at) BETWEEN $7 AND COALESCE($8, CURRENT_DATE) )\n        ORDER BY\n        SIMILARITY(CASE \n            WHEN $1 = 'en_us' THEN en_us\n            WHEN $1 = 'de_de' THEN de_de\n            WHEN $1 = 'fr_fr' THEN fr_fr\n            WHEN $1 = 'ru_ru' THEN ru_ru\n            WHEN $1 = 'pl_pl' THEN pl_pl\n            WHEN $1 = 'es_es' THEN es_es\n            WHEN $1 = 'pt_br' THEN pt_br\n            WHEN $1 = 'it_it' THEN it_it\n            WHEN $1 = 'zh_cn' THEN zh_cn\n            WHEN $1 = 'ko_kr' THEN ko_kr\n            WHEN $1 = 'ja_jp' THEN ja_jp\n            WHEN $1 = 'zh_tw' THEN zh_tw\n            WHEN $1 = 'id_id' THEN id_id\n        END, $2) DESC,\n        unit_price_silver ASC\n        OFFSET $9\n        LIMIT $10",
  "describe": {
    "columns": [
      {
        "ordinal": 0,
        "name": "id",
        "type_info": "Int8"
      },
      {
        "ordinal": 1,
        "name": "location_id",
        "type_info": "Text"
      },
      {
        "ordinal": 2,
        "name": "item_unique_name",
        "type_info": "Text"
      },
      {
        "ordinal": 3,
        "name": "quality_level",
        "type_info": "Int4"
      },
      {
        "ordinal": 4,
        "name": "enchantment_level",
        "type_info": "Int4"
      },
      {
        "ordinal": 5,
        "name": "unit_price_silver",
        "type_info": "Int4"
      },
      {
        "ordinal": 6,
        "name": "amount",
        "type_info": "Int4"
      },
      {
        "ordinal": 7,
        "name": "auction_type",
        "type_info": "Text"
      },
      {
        "ordinal": 8,
        "name": "expires_at",
        "type_info": "Timestamp"
      },
      {
        "ordinal": 9,
        "name": "updated_at",
        "type_info": "Timestamp"
      },
      {
        "ordinal": 10,
        "name": "created_at",
        "type_info": "Timestamp"
      }
    ],
    "parameters": {
      "Left": [
        "Text",
        "Text",
        "Text",
        "Text",
        "Int4",
        "Int4",
        "Date",
        "Date",
        "Int8",
        "Int8"
      ]
    },
    "nullable": [
      false,
      false,
      false,
      false,
      false,
      false,
      false,
      false,
      false,
      false,
      false
    ]
  },
  "hash": "a3b099a5359834a18fa6c303e408803c96a2b10ed3e591a021d1e8807009fe4b"
}
